PySimpleGUIWx/PySimpleGUIWx.py
PySimpleGUIWx/__init__.py
PySimpleGUIWx-0.17.2.dist-info/METADATA
PySimpleGUIWx-0.17.2.dist-info/WHEEL
PySimpleGUIWx-0.17.2.dist-info/top_level.txt
PySimpleGUIWx-0.17.2.dist-info/RECORD
