Metadata-Version: 2.1
Name: PySimpleGUIWx
Version: 0.17.2
Summary: The Engineering Pre-Release WxPython version of PySimpleGUI. PySimpleGUI SDK Launched in 2018 Actively developed and supported. Super-simple to create custom GUI's.  Now supports tkinter, Qt, WxPython, and Remi
Home-page: https://github.com/PySimpleGUI/PySimpleGUI
Author: MikeTheWatchGuy
Author-email: PySimpleGUI@PySimpleGUI.org
License: UNKNOWN
Keywords: GUI UI tkinter wrapper simple easy beginner novice student graphics progressbar progressmeter
Platform: UNKNOWN
Classifier: Programming Language :: Python :: 3
Classifier: Programming Language :: Python :: 3.4
Classifier: Programming Language :: Python :: 3.5
Classifier: Programming Language :: Python :: 3.6
Classifier: Programming Language :: Python :: 3.7
Classifier: Programming Language :: Python :: 3.8
Classifier: License :: OSI Approved :: GNU Lesser General Public License v3 or later (LGPLv3+)
Classifier: Topic :: Multimedia :: Graphics
Classifier: Operating System :: OS Independent
